.gitignore
README.rst
TODO.rst
bootstrap.py
buildout.cfg
setup.py
docs/CHANGES.rst
docs/CONTRIBUTORS.rst
docs/LICENSE.txt
docs/Makefile
docs/api.rst
docs/conf.py
docs/index.rst
docs/make.bat
src/telstra/__init__.py
src/telstra.mobile.egg-info/PKG-INFO
src/telstra.mobile.egg-info/SOURCES.txt
src/telstra.mobile.egg-info/dependency_links.txt
src/telstra.mobile.egg-info/entry_points.txt
src/telstra.mobile.egg-info/namespace_packages.txt
src/telstra.mobile.egg-info/not-zip-safe
src/telstra.mobile.egg-info/requires.txt
src/telstra.mobile.egg-info/top_level.txt
src/telstra/mobile/__init__.py
src/telstra/mobile/account.py
src/telstra/mobile/config.py
src/telstra/mobile/modem.py
src/telstra/mobile/web.py
src/telstra/mobile/scripts/__init__.py
src/telstra/mobile/scripts/send_credit.py
src/telstra/mobile/tests/__init__.py
src/telstra/mobile/tests/test_account.py
src/telstra/mobile/tests/test_modem.py