Metadata-Version: 1.1
Name: telstra.mobile
Version: 0.1
Summary: API for interacting with Telstra's mobile services via cellular modem
Home-page: https://github.com/davidjb/telstra.mobile
Author: David Beitey
Author-email: david@davidjb.com
License: MIT
Keywords: Modem Serial pySerial GSM Telstra Cellular Modem
Platform: UNKNOWN
Classifier: Programming Language :: Python
Classifier: Development Status :: 1 - Planning
Classifier: Environment :: Console
Classifier: Intended Audience :: Developers
Classifier: License :: OSI Approved :: MIT License
Classifier: Operating System :: OS Independent
Classifier: Topic :: Software Development :: Libraries :: Python Modules
